zipcode_to_map/__init__.py
zipcode_to_map/example_usage.py
zipcode_to_map/setup.py
zipcode_to_map/zipcode_to_map.py
zipcode_to_map-1.0.dist-info/METADATA
zipcode_to_map-1.0.dist-info/WHEEL
zipcode_to_map-1.0.dist-info/top_level.txt
zipcode_to_map-1.0.dist-info/RECORD
