Metadata-Version: 2.1
Name: zipcode-to-map
Version: 1.0
Summary: Provide a Country code and postal code.It will generate a map in a html file based on these details.Used pgeocode and folium packages.
Home-page: https://github.com/bharathjinka09/zipcode_to_map
Author: JINKA RANGA BHARATH
Author-email: bharathjinka09@gmail.com
License: UNKNOWN
Download-URL: https://github.com/bharathjinka09/zipcode_to_map/archive/1.0.tar.gz
Keywords: zipcode,HTML map file
Platform: UNKNOWN
Requires-Python: >=3.7
